calh/__init__.py
calh/app.py
calh/cli.py
calh/filter.py
calh/visualization.py
calh-2.2.1.dist-info/AUTHORS.rst
calh-2.2.1.dist-info/LICENSE
calh-2.2.1.dist-info/METADATA
calh-2.2.1.dist-info/WHEEL
calh-2.2.1.dist-info/entry_points.txt
calh-2.2.1.dist-info/top_level.txt
calh-2.2.1.dist-info/RECORD
