Metadata-Version: 2.1
Name: calh
Version: 2.2.1
Summary: Calendar Heatmap
Home-page: https://github.com/ricky-lim/calh
Author: Ricky Lim
Author-email: rlim.email@gmail.com
License: Apache Software License 2.0
Keywords: calh
Platform: UNKNOWN
Classifier: Development Status :: 2 - Pre-Alpha
Classifier: Intended Audience :: Developers
Classifier: License :: OSI Approved :: Apache Software License
Classifier: Natural Language :: English
Classifier: Programming Language :: Python :: 3
Classifier: Programming Language :: Python :: 3.5
Classifier: Programming Language :: Python :: 3.6
Classifier: Programming Language :: Python :: 3.7
Classifier: Programming Language :: Python :: 3.8
Requires-Python: >=3.6
Requires-Dist: Click (>=7.0)
Requires-Dist: click-spinner (>=0.1.10)
Requires-Dist: ics (>=0.7)
Requires-Dist: matplotlib (>=3.2.1)
Requires-Dist: notebook (>=6.0.3)
Requires-Dist: numpy (>=1.18.3)
Requires-Dist: pandas (>=1.0.3)
Requires-Dist: pyprojroot (>=0.2.0)
Requires-Dist: seaborn (>=0.10.1)
Requires-Dist: voila (>=0.1.21)
Requires-Dist: ipyvuetify (>=1.4.0)
Requires-Dist: ipympl (>=0.5.6)
